cleano/__init__.py
cleano/cleaning.py
cleano/preprocessing.py
cleano/utils.py
cleano-0.1.0.dist-info/METADATA
cleano-0.1.0.dist-info/WHEEL
cleano-0.1.0.dist-info/top_level.txt
cleano-0.1.0.dist-info/RECORD
